[{"chapter":79,"text":"O God, the heathen are come into thine inheritance; thy holy       temple have they defiled; they have laid Jerusalem on heaps.","verse":1,"book":"Psalms","reference":[{"index":0,"strongs":0,"text":"O "},{"index":1,"strongs":"H04210","text":"god,"},{"index":2,"strongs":0,"text":"the"},{"index":3,"strongs":"H0623","text":"heathen"},{"index":4,"strongs":0,"text":"are"},{"index":5,"strongs":"H0430","text":"come"},{"index":6,"strongs":0,"text":"into"},{"index":7,"strongs":"H01471","text":"thine"},{"index":8,"strongs":0,"text":"inheritance;"},{"index":9,"strongs":"H0935","text":"thy"},{"index":10,"strongs":0,"text":"holy temple"},{"index":11,"strongs":"H05159","text":"have"},{"index":12,"strongs":0,"text":"they"},{"index":13,"strongs":"H06944","text":"defiled;"},{"index":14,"strongs":"H01964","text":"they"},{"index":15,"strongs":0,"text":"have laid"},{"index":16,"strongs":"H02930","text":"Jerusalem"},{"index":17,"strongs":0,"text":"on heaps."}]},{"chapter":79,"text":"The dead bodies of thy servants have they given [to be] meat       unto the fowls of the heaven, the flesh of thy saints unto the       beasts of the earth.","verse":2,"book":"Psalms","reference":[{"index":0,"strongs":0,"text":"The dead "},{"index":1,"strongs":"H05038","text":"bodies"},{"index":2,"strongs":0,"text":"of thy"},{"index":3,"strongs":"H05650","text":"servants"},{"index":4,"strongs":0,"text":"have they"},{"index":5,"strongs":"H05414","text":"given"},{"index":6,"strongs":0,"text":"to be"},{"index":7,"strongs":"H03978","text":"meat"},{"index":8,"strongs":0,"text":"unto the"},{"index":9,"strongs":"H05775","text":"fowls"},{"index":10,"strongs":0,"text":"of the"},{"index":11,"strongs":"H08064","text":"heaven,"},{"index":12,"strongs":0,"text":"the"},{"index":13,"strongs":"H01320","text":"flesh"},{"index":14,"strongs":0,"text":"of thy"},{"index":15,"strongs":"H02623","text":"saints"},{"index":16,"strongs":0,"text":"unto the"},{"index":17,"strongs":"H02416","text":"beasts"},{"index":18,"strongs":0,"text":"of the"},{"index":19,"strongs":"H0776","text":"earth."}]},{"chapter":79,"text":"Their blood have they shed like water round about Jerusalem; and       [there was] none to bury [them.]","verse":3,"book":"Psalms","reference":[{"index":0,"strongs":0,"text":"Their "},{"index":1,"strongs":"H01818","text":"blood"},{"index":2,"strongs":0,"text":"have they"},{"index":3,"strongs":"H08210","text":"shed"},{"index":4,"strongs":0,"text":"like"},{"index":5,"strongs":"H04325","text":"water"},{"index":6,"strongs":0,"text":"round"},{"index":7,"strongs":"H05439","text":"about"},{"index":8,"strongs":"H03389","text":"Jerusalem;"},{"index":9,"strongs":0,"text":"and there was none to"},{"index":10,"strongs":"H06912","text":"bury"},{"index":11,"strongs":0,"text":"them."}]},{"chapter":79,"text":"We are become a reproach to our neighbours, a scorn and derision       to them that are round about us.","verse":4,"book":"Psalms","reference":[{"index":0,"strongs":0,"text":"We are become a "},{"index":1,"strongs":"H02781","text":"reproach"},{"index":2,"strongs":0,"text":"to our"},{"index":3,"strongs":"H07934","text":"neighbours,"},{"index":4,"strongs":0,"text":"a"},{"index":5,"strongs":"H03933","text":"scorn"},{"index":6,"strongs":0,"text":"and"},{"index":7,"strongs":"H07047","text":"derision"},{"index":8,"strongs":0,"text":"to them that are round"},{"index":9,"strongs":"H05439","text":"about"},{"index":10,"strongs":0,"text":"us."}]},{"chapter":79,"text":"How long, LORD? wilt thou be angry for ever? shall thy jealousy       burn like fire?","verse":5,"book":"Psalms","reference":[{"index":0,"strongs":0,"text":"How long, "},{"index":1,"strongs":"H03068","text":"LORD?"},{"index":2,"strongs":0,"text":"wilt thou be"},{"index":3,"strongs":"H0599","text":"angry"},{"index":4,"strongs":0,"text":"for"},{"index":5,"strongs":"H05331","text":"ever?"},{"index":6,"strongs":0,"text":"shall thy"},{"index":7,"strongs":"H07068","text":"jealousy"},{"index":8,"strongs":"H01197","text":"burn"},{"index":9,"strongs":0,"text":"like"},{"index":10,"strongs":"H0784","text":"fire?"}]},{"chapter":79,"text":"Pour out thy wrath upon the heathen that have not known thee,       and upon the kingdoms that have not called upon thy name.","verse":6,"book":"Psalms","reference":[{"index":0,"strongs":0,"text":"Pour "},{"index":1,"strongs":"H08210","text":"out"},{"index":2,"strongs":0,"text":"thy"},{"index":3,"strongs":"H02534","text":"wrath"},{"index":4,"strongs":0,"text":"upon the"},{"index":5,"strongs":"H01471","text":"heathen"},{"index":6,"strongs":0,"text":"that have not"},{"index":7,"strongs":"H03045","text":"known"},{"index":8,"strongs":0,"text":"thee, and upon the"},{"index":9,"strongs":"H04467","text":"kingdoms"},{"index":10,"strongs":0,"text":"that have not"},{"index":11,"strongs":"H07121","text":"called"},{"index":12,"strongs":0,"text":"upon thy"},{"index":13,"strongs":"H08034","text":"name."}]},{"chapter":79,"text":"For they have devoured Jacob, and laid waste his dwelling place.","verse":7,"book":"Psalms","reference":[{"index":0,"strongs":0,"text":"For they have "},{"index":1,"strongs":"H0398","text":"devoured"},{"index":2,"strongs":"H03290","text":"Jacob,"},{"index":3,"strongs":0,"text":"and laid"},{"index":4,"strongs":"H08074","text":"waste"},{"index":5,"strongs":0,"text":"his dwelling"},{"index":6,"strongs":"H05116","text":"place."}]},{"chapter":79,"text":"O remember not against us former iniquities: let thy tender       mercies speedily prevent us: for we are brought very low.","verse":8,"book":"Psalms","reference":[{"index":0,"strongs":0,"text":"O "},{"index":1,"strongs":"H02142","text":"remember"},{"index":2,"strongs":0,"text":"not against us"},{"index":3,"strongs":"H07223","text":"former"},{"index":4,"strongs":"H05771","text":"iniquities:"},{"index":5,"strongs":0,"text":"let thy tender"},{"index":6,"strongs":"H07356","text":"mercies"},{"index":7,"strongs":"H04118","text":"speedily"},{"index":8,"strongs":"H06923","text":"prevent"},{"index":9,"strongs":0,"text":"us: for we are"},{"index":10,"strongs":"H01809","text":"brought"},{"index":11,"strongs":"H03966","text":"very"},{"index":12,"strongs":"H01809","text":"low."}]},{"chapter":79,"text":"Help us, O God of our salvation, for the glory of thy name: and       deliver us, and purge away our sins, for thy name's sake.","verse":9,"book":"Psalms","reference":[{"index":0,"strongs":"H05826","text":"Help"},{"index":1,"strongs":0,"text":"us, O"},{"index":2,"strongs":"H0430","text":"God"},{"index":3,"strongs":0,"text":"of our"},{"index":4,"strongs":"H03468","text":"salvation,"},{"index":5,"strongs":"H01697","text":"for"},{"index":6,"strongs":0,"text":"the"},{"index":7,"strongs":"H03519","text":"glory"},{"index":8,"strongs":0,"text":"of thy"},{"index":9,"strongs":"H08034","text":"name:"},{"index":10,"strongs":0,"text":"and"},{"index":11,"strongs":"H05337","text":"deliver"},{"index":12,"strongs":0,"text":"us, and purge"},{"index":13,"strongs":"H03722","text":"away"},{"index":14,"strongs":0,"text":"our"},{"index":15,"strongs":"H02403","text":"sins,"},{"index":16,"strongs":0,"text":"for thy"},{"index":17,"strongs":"H08034","text":"name's"},{"index":18,"strongs":0,"text":"sake."}]},{"chapter":79,"text":"Wherefore should the heathen say, Where [is] their God? let him       be known among the heathen in our sight [by] the revenging of the       blood of thy servants [which is] shed.","verse":10,"book":"Psalms","reference":[{"index":0,"strongs":0,"text":"Wherefore should the "},{"index":1,"strongs":"H01471","text":"heathen"},{"index":2,"strongs":"H0559","text":"say,"},{"index":3,"strongs":0,"text":"Where is their"},{"index":4,"strongs":"H0430","text":"God?"},{"index":5,"strongs":0,"text":"let him be"},{"index":6,"strongs":"H03045","text":"known"},{"index":7,"strongs":0,"text":"among the"},{"index":8,"strongs":"H01471","text":"heathen"},{"index":9,"strongs":0,"text":"in our"},{"index":10,"strongs":"H05869","text":"sight"},{"index":11,"strongs":0,"text":"by the"},{"index":12,"strongs":"H05360","text":"revenging"},{"index":13,"strongs":0,"text":"of the"},{"index":14,"strongs":"H01818","text":"blood"},{"index":15,"strongs":0,"text":"of thy"},{"index":16,"strongs":"H05650","text":"servants"},{"index":17,"strongs":0,"text":"which is"},{"index":18,"strongs":"H08210","text":"shed."}]},{"chapter":79,"text":"Let the sighing of the prisoner come before thee; according to       the greatness of thy power preserve thou those that are appointed       to die;","verse":11,"book":"Psalms","reference":[{"index":0,"strongs":0,"text":"Let the "},{"index":1,"strongs":"H0603","text":"sighing"},{"index":2,"strongs":0,"text":"of the"},{"index":3,"strongs":"H0615","text":"prisoner"},{"index":4,"strongs":"H0935","text":"come"},{"index":5,"strongs":"H06440","text":"before"},{"index":6,"strongs":0,"text":"thee; according to the"},{"index":7,"strongs":"H01433","text":"greatness"},{"index":8,"strongs":0,"text":"of thy"},{"index":9,"strongs":"H02220","text":"power"},{"index":10,"strongs":"H03498","text":"preserve"},{"index":11,"strongs":0,"text":"thou those that are"},{"index":12,"strongs":"H01121","text":"appointed"},{"index":13,"strongs":0,"text":"to"},{"index":14,"strongs":"H08546","text":"die;"}]},{"chapter":79,"text":"And render unto our neighbours sevenfold into their bosom their       reproach, wherewith they have reproached thee, O Lord.","verse":12,"book":"Psalms","reference":[{"index":0,"strongs":0,"text":"And "},{"index":1,"strongs":"H07725","text":"render"},{"index":2,"strongs":0,"text":"unto our"},{"index":3,"strongs":"H07934","text":"neighbours"},{"index":4,"strongs":"H07659","text":"sevenfold"},{"index":5,"strongs":0,"text":"into their"},{"index":6,"strongs":"H02436","text":"bosom"},{"index":7,"strongs":0,"text":"their"},{"index":8,"strongs":"H02781","text":"reproach,"},{"index":9,"strongs":0,"text":"wherewith they have"},{"index":10,"strongs":"H02778","text":"reproached"},{"index":11,"strongs":0,"text":"thee, O"},{"index":12,"strongs":"H0136","text":"Lord."}]},{"chapter":79,"text":"So we thy people and sheep of thy pasture will give thee thanks       for ever: we will shew forth thy praise to all generations.   Psalm 80  To the chief Musician upon Shoshannim-Eduth, A Psalm of Asaph.","verse":13,"book":"Psalms","reference":[{"index":0,"strongs":0,"text":"So we thy "},{"index":1,"strongs":"H05971","text":"people"},{"index":2,"strongs":0,"text":"and"},{"index":3,"strongs":"H06629","text":"sheep"},{"index":4,"strongs":0,"text":"of thy"},{"index":5,"strongs":"H04830","text":"pasture"},{"index":6,"strongs":0,"text":"will give thee"},{"index":7,"strongs":"H03034","text":"thanks"},{"index":8,"strongs":0,"text":"for"},{"index":9,"strongs":"H05769","text":"ever:"},{"index":10,"strongs":0,"text":"we will shew"},{"index":11,"strongs":"H05608","text":"forth"},{"index":12,"strongs":0,"text":"thy"},{"index":13,"strongs":"H08416","text":"praise"},{"index":14,"strongs":0,"text":"to"},{"index":15,"strongs":"H01755","text":"all"},{"index":16,"strongs":"H01755","text":"generations."}]}]