[{"chapter":26,"text":"And it came to pass after the plague, that the LORD spake unto Moses and unto Eleazar the son of Aaron the priest, saying,","verse":1,"book":"Numbers","reference":[{"index":0,"strongs":0,"text":"And it came to pass "},{"index":1,"strongs":"H0310","text":"after"},{"index":2,"strongs":0,"text":"the"},{"index":3,"strongs":"H04046","text":"plague,"},{"index":4,"strongs":0,"text":"that the"},{"index":5,"strongs":"H03068","text":"LORD"},{"index":6,"strongs":"H0559","text":"spake"},{"index":7,"strongs":0,"text":"unto"},{"index":8,"strongs":"H04872","text":"Moses"},{"index":9,"strongs":0,"text":"and unto"},{"index":10,"strongs":"H0499","text":"Eleazar"},{"index":11,"strongs":0,"text":"the"},{"index":12,"strongs":"H01121","text":"son"},{"index":13,"strongs":0,"text":"of"},{"index":14,"strongs":"H0175","text":"Aaron"},{"index":15,"strongs":0,"text":"the"},{"index":16,"strongs":"H03548","text":"priest,"},{"index":17,"strongs":"H0559","text":"saying,"}]},{"chapter":26,"text":"Take the sum of all the congregation of the children of Israel, from twenty years old and upward, throughout their fathers' house, all that are able to go to war in Israel.","verse":2,"book":"Numbers","reference":[{"index":0,"strongs":"H05375","text":"Take"},{"index":1,"strongs":0,"text":"the"},{"index":2,"strongs":"H07218","text":"sum"},{"index":3,"strongs":0,"text":"of all the"},{"index":4,"strongs":"H05712","text":"congregation"},{"index":5,"strongs":0,"text":"of the"},{"index":6,"strongs":"H01121","text":"children"},{"index":7,"strongs":0,"text":"of"},{"index":8,"strongs":"H03478","text":"Israel,"},{"index":9,"strongs":0,"text":"from"},{"index":10,"strongs":"H06242","text":"twenty"},{"index":11,"strongs":"H08141","text":"years"},{"index":12,"strongs":"H01121","text":"old"},{"index":13,"strongs":0,"text":"and"},{"index":14,"strongs":"H04605","text":"upward,"},{"index":15,"strongs":0,"text":"throughout their"},{"index":16,"strongs":"H0001","text":"fathers'"},{"index":17,"strongs":"H01004","text":"house,"},{"index":18,"strongs":0,"text":"all that are able to"},{"index":19,"strongs":"H03318","text":"go"},{"index":20,"strongs":0,"text":"to"},{"index":21,"strongs":"H06635","text":"war"},{"index":22,"strongs":0,"text":"in"},{"index":23,"strongs":"H03478","text":"Israel."}]},{"chapter":26,"text":"And Moses and Eleazar the priest spake with them in the plains of Moab by Jordan [near] Jericho, saying,","verse":3,"book":"Numbers","reference":[{"index":0,"strongs":0,"text":"And "},{"index":1,"strongs":"H04872","text":"Moses"},{"index":2,"strongs":0,"text":"and"},{"index":3,"strongs":"H0499","text":"Eleazar"},{"index":4,"strongs":0,"text":"the"},{"index":5,"strongs":"H03548","text":"priest"},{"index":6,"strongs":"H01696","text":"spake"},{"index":7,"strongs":0,"text":"with them in the"},{"index":8,"strongs":"H06160","text":"plains"},{"index":9,"strongs":0,"text":"of"},{"index":10,"strongs":"H04124","text":"Moab"},{"index":11,"strongs":0,"text":"by"},{"index":12,"strongs":"H03383","text":"Jordan"},{"index":13,"strongs":0,"text":"near"},{"index":14,"strongs":"H03405","text":"Jericho,"},{"index":15,"strongs":"H0559","text":"saying,"}]},{"chapter":26,"text":"[Take the sum of the people,] from twenty years old and upward; as the LORD commanded Moses and the children of Israel, which went forth out of the land of Egypt.","verse":4,"book":"Numbers","reference":[{"index":0,"strongs":0,"text":"Take the sum of the people, from "},{"index":1,"strongs":"H06242","text":"twenty"},{"index":2,"strongs":"H08141","text":"years"},{"index":3,"strongs":"H01121","text":"old"},{"index":4,"strongs":0,"text":"and"},{"index":5,"strongs":"H04605","text":"upward;"},{"index":6,"strongs":0,"text":"as the"},{"index":7,"strongs":"H03068","text":"LORD"},{"index":8,"strongs":"H06680","text":"commanded"},{"index":9,"strongs":"H04872","text":"Moses"},{"index":10,"strongs":0,"text":"and the"},{"index":11,"strongs":"H01121","text":"children"},{"index":12,"strongs":0,"text":"of"},{"index":13,"strongs":"H03478","text":"Israel,"},{"index":14,"strongs":0,"text":"which went"},{"index":15,"strongs":"H03318","text":"forth"},{"index":16,"strongs":0,"text":"out of the"},{"index":17,"strongs":"H0776","text":"land"},{"index":18,"strongs":0,"text":"of"},{"index":19,"strongs":"H04714","text":"Egypt."}]},{"chapter":26,"text":"Reuben, the eldest son of Israel: the children of Reuben; Hanoch, [of whom cometh] the family of the Hanochites: of Pallu, the family of the Palluites:","verse":5,"book":"Numbers","reference":[{"index":0,"strongs":"H07205","text":"Reuben,"},{"index":1,"strongs":0,"text":"the"},{"index":2,"strongs":"H01060","text":"eldest"},{"index":3,"strongs":0,"text":"son of"},{"index":4,"strongs":"H03478","text":"Israel:"},{"index":5,"strongs":0,"text":"the"},{"index":6,"strongs":"H01121","text":"children"},{"index":7,"strongs":0,"text":"of"},{"index":8,"strongs":"H07205","text":"Reuben;"},{"index":9,"strongs":"H02585","text":"Hanoch,"},{"index":10,"strongs":0,"text":"of whom cometh the"},{"index":11,"strongs":"H04940","text":"family"},{"index":12,"strongs":0,"text":"of the"},{"index":13,"strongs":"H02599","text":"Hanochites:"},{"index":14,"strongs":0,"text":"of"},{"index":15,"strongs":"H06396","text":"Pallu,"},{"index":16,"strongs":0,"text":"the"},{"index":17,"strongs":"H04940","text":"family"},{"index":18,"strongs":0,"text":"of the"},{"index":19,"strongs":"H06384","text":"Palluites:"}]},{"chapter":26,"text":"Of Hezron, the family of the Hezronites: of Carmi, the family of the Carmites.","verse":6,"book":"Numbers","reference":[{"index":0,"strongs":0,"text":"Of "},{"index":1,"strongs":"H02696","text":"Hezron,"},{"index":2,"strongs":0,"text":"the"},{"index":3,"strongs":"H04940","text":"family"},{"index":4,"strongs":0,"text":"of the"},{"index":5,"strongs":"H02697","text":"Hezronites:"},{"index":6,"strongs":0,"text":"of"},{"index":7,"strongs":"H03756","text":"Carmi,"},{"index":8,"strongs":0,"text":"the"},{"index":9,"strongs":"H04940","text":"family"},{"index":10,"strongs":0,"text":"of the"},{"index":11,"strongs":"H03757","text":"Carmites."}]},{"chapter":26,"text":"These [are] the families of the Reubenites: and they that were numbered of them were forty and three thousand and seven hundred and thirty.","verse":7,"book":"Numbers","reference":[{"index":0,"strongs":0,"text":"These are the "},{"index":1,"strongs":"H04940","text":"families"},{"index":2,"strongs":0,"text":"of the"},{"index":3,"strongs":"H07206","text":"Reubenites:"},{"index":4,"strongs":0,"text":"and they that were"},{"index":5,"strongs":"H06485","text":"numbered"},{"index":6,"strongs":0,"text":"of them were"},{"index":7,"strongs":"H0705","text":"forty"},{"index":8,"strongs":0,"text":"and"},{"index":9,"strongs":"H07969","text":"three"},{"index":10,"strongs":"H0505","text":"thousand"},{"index":11,"strongs":0,"text":"and"},{"index":12,"strongs":"H07651","text":"seven"},{"index":13,"strongs":"H03967","text":"hundred"},{"index":14,"strongs":0,"text":"and"},{"index":15,"strongs":"H07970","text":"thirty."}]},{"chapter":26,"text":"And the sons of Pallu; Eliab.","verse":8,"book":"Numbers","reference":[{"index":0,"strongs":0,"text":"And the "},{"index":1,"strongs":"H01121","text":"sons"},{"index":2,"strongs":0,"text":"of"},{"index":3,"strongs":"H06396","text":"Pallu;"},{"index":4,"strongs":"H0446","text":"Eliab."}]},{"chapter":26,"text":"And the sons of Eliab; Nemuel, and Dathan, and Abiram. This [is that] Dathan and Abiram, [which were] famous in the congregation, who strove against Moses and against Aaron in the company of Korah, when they strove against the LORD:","verse":9,"book":"Numbers","reference":[{"index":0,"strongs":0,"text":"And the "},{"index":1,"strongs":"H01121","text":"sons"},{"index":2,"strongs":0,"text":"of"},{"index":3,"strongs":"H0446","text":"Eliab;"},{"index":4,"strongs":"H05241","text":"Nemuel,"},{"index":5,"strongs":0,"text":"and"},{"index":6,"strongs":"H01885","text":"Dathan,"},{"index":7,"strongs":0,"text":"and"},{"index":8,"strongs":"H0048","text":"Abiram."},{"index":9,"strongs":0,"text":"This is that"},{"index":10,"strongs":"H01885","text":"Dathan"},{"index":11,"strongs":0,"text":"and"},{"index":12,"strongs":"H0048","text":"Abiram,"},{"index":13,"strongs":0,"text":"which were"},{"index":14,"strongs":"H07121","text":"famous"},{"index":15,"strongs":"H07148","text":"in"},{"index":16,"strongs":0,"text":"the congregation,"},{"index":17,"strongs":"H05712","text":"who"},{"index":18,"strongs":0,"text":"strove"},{"index":19,"strongs":"H05327","text":"against"},{"index":20,"strongs":0,"text":"Moses"},{"index":21,"strongs":"H04872","text":"and"},{"index":22,"strongs":0,"text":"against Aaron"},{"index":23,"strongs":"H0175","text":"in"},{"index":24,"strongs":0,"text":"the company"},{"index":25,"strongs":"H05712","text":"of"},{"index":26,"strongs":0,"text":"Korah,"},{"index":27,"strongs":"H07141","text":"when"},{"index":28,"strongs":0,"text":"they strove"},{"index":29,"strongs":"H05327","text":"against"},{"index":30,"strongs":0,"text":"the LORD:"}]},{"chapter":26,"text":"And the earth opened her mouth, and swallowed them up together with Korah, when that company died, what time the fire devoured two hundred and fifty men: and they became a sign.","verse":10,"book":"Numbers","reference":[{"index":0,"strongs":0,"text":"And the "},{"index":1,"strongs":"H0776","text":"earth"},{"index":2,"strongs":"H06605","text":"opened"},{"index":3,"strongs":0,"text":"her"},{"index":4,"strongs":"H06310","text":"mouth,"},{"index":5,"strongs":0,"text":"and swallowed them"},{"index":6,"strongs":"H01104","text":"up"},{"index":7,"strongs":0,"text":"together with"},{"index":8,"strongs":"H07141","text":"Korah,"},{"index":9,"strongs":0,"text":"when that"},{"index":10,"strongs":"H05712","text":"company"},{"index":11,"strongs":"H04194","text":"died,"},{"index":12,"strongs":0,"text":"what time the"},{"index":13,"strongs":"H0784","text":"fire"},{"index":14,"strongs":"H0398","text":"devoured"},{"index":15,"strongs":0,"text":"two"},{"index":16,"strongs":"H03967","text":"hundred"},{"index":17,"strongs":0,"text":"and"},{"index":18,"strongs":"H02572","text":"fifty"},{"index":19,"strongs":"H0376","text":"men:"},{"index":20,"strongs":0,"text":"and they became a"},{"index":21,"strongs":"H05251","text":"sign."}]},{"chapter":26,"text":"Notwithstanding the children of Korah died not.","verse":11,"book":"Numbers","reference":[{"index":0,"strongs":0,"text":"Notwithstanding the "},{"index":1,"strongs":"H01121","text":"children"},{"index":2,"strongs":0,"text":"of"},{"index":3,"strongs":"H07141","text":"Korah"},{"index":4,"strongs":"H04191","text":"died"},{"index":5,"strongs":0,"text":"not."}]},{"chapter":26,"text":"The sons of Simeon after their families: of Nemuel, the family of the Nemuelites: of Jamin, the family of the Jaminites: of Jachin, the family of the Jachinites:","verse":12,"book":"Numbers","reference":[{"index":0,"strongs":0,"text":"The "},{"index":1,"strongs":"H01121","text":"sons"},{"index":2,"strongs":0,"text":"of"},{"index":3,"strongs":"H08095","text":"Simeon"},{"index":4,"strongs":0,"text":"after their"},{"index":5,"strongs":"H04940","text":"families:"},{"index":6,"strongs":0,"text":"of"},{"index":7,"strongs":"H05241","text":"Nemuel,"},{"index":8,"strongs":0,"text":"the"},{"index":9,"strongs":"H04940","text":"family"},{"index":10,"strongs":0,"text":"of the"},{"index":11,"strongs":"H05242","text":"Nemuelites:"},{"index":12,"strongs":0,"text":"of"},{"index":13,"strongs":"H03226","text":"Jamin,"},{"index":14,"strongs":0,"text":"the"},{"index":15,"strongs":"H04940","text":"family"},{"index":16,"strongs":0,"text":"of the"},{"index":17,"strongs":"H03228","text":"Jaminites:"},{"index":18,"strongs":0,"text":"of"},{"index":19,"strongs":"H03199","text":"Jachin,"},{"index":20,"strongs":0,"text":"the"},{"index":21,"strongs":"H04940","text":"family"},{"index":22,"strongs":0,"text":"of the"},{"index":23,"strongs":"H03200","text":"Jachinites:"}]},{"chapter":26,"text":"Of Zerah, the family of the Zarhites: of Shaul, the family of the Shaulites.","verse":13,"book":"Numbers","reference":[{"index":0,"strongs":0,"text":"Of "},{"index":1,"strongs":"H02226","text":"Zerah,"},{"index":2,"strongs":0,"text":"the"},{"index":3,"strongs":"H04940","text":"family"},{"index":4,"strongs":0,"text":"of the"},{"index":5,"strongs":"H02227","text":"Zarhites:"},{"index":6,"strongs":0,"text":"of"},{"index":7,"strongs":"H07586","text":"Shaul,"},{"index":8,"strongs":0,"text":"the"},{"index":9,"strongs":"H04940","text":"family"},{"index":10,"strongs":0,"text":"of the"},{"index":11,"strongs":"H07587","text":"Shaulites."}]},{"chapter":26,"text":"These [are] the families of the Simeonites, twenty and two thousand and two hundred.","verse":14,"book":"Numbers","reference":[{"index":0,"strongs":0,"text":"These are the "},{"index":1,"strongs":"H04940","text":"families"},{"index":2,"strongs":0,"text":"of the"},{"index":3,"strongs":"H08099","text":"Simeonites,"},{"index":4,"strongs":"H06242","text":"twenty"},{"index":5,"strongs":0,"text":"and"},{"index":6,"strongs":"H08147","text":"two"},{"index":7,"strongs":"H0505","text":"thousand"},{"index":8,"strongs":0,"text":"and two"},{"index":9,"strongs":"H03967","text":"hundred."}]},{"chapter":26,"text":"The children of Gad after their families: of Zephon, the family of the Zephonites: of Haggi, the family of the Haggites: of Shuni, the family of the Shunites:","verse":15,"book":"Numbers","reference":[{"index":0,"strongs":0,"text":"The "},{"index":1,"strongs":"H01121","text":"children"},{"index":2,"strongs":0,"text":"of"},{"index":3,"strongs":"H01410","text":"Gad"},{"index":4,"strongs":0,"text":"after their"},{"index":5,"strongs":"H04940","text":"families:"},{"index":6,"strongs":0,"text":"of"},{"index":7,"strongs":"H06827","text":"Zephon,"},{"index":8,"strongs":0,"text":"the"},{"index":9,"strongs":"H04940","text":"family"},{"index":10,"strongs":0,"text":"of the"},{"index":11,"strongs":"H06831","text":"Zephonites:"},{"index":12,"strongs":0,"text":"of"},{"index":13,"strongs":"H02291","text":"Haggi,"},{"index":14,"strongs":0,"text":"the"},{"index":15,"strongs":"H04940","text":"family"},{"index":16,"strongs":0,"text":"of the"},{"index":17,"strongs":"H02291","text":"Haggites:"},{"index":18,"strongs":0,"text":"of"},{"index":19,"strongs":"H07764","text":"Shuni,"},{"index":20,"strongs":0,"text":"the"},{"index":21,"strongs":"H04940","text":"family"},{"index":22,"strongs":0,"text":"of the"},{"index":23,"strongs":"H07765","text":"Shunites:"}]},{"chapter":26,"text":"Of Ozni, the family of the Oznites: of Eri, the family of the Erites:","verse":16,"book":"Numbers","reference":[{"index":0,"strongs":0,"text":"Of "},{"index":1,"strongs":"H0244","text":"Ozni,"},{"index":2,"strongs":0,"text":"the"},{"index":3,"strongs":"H04940","text":"family"},{"index":4,"strongs":0,"text":"of the"},{"index":5,"strongs":"H0244","text":"Oznites:"},{"index":6,"strongs":0,"text":"of"},{"index":7,"strongs":"H06179","text":"Eri,"},{"index":8,"strongs":0,"text":"the"},{"index":9,"strongs":"H04940","text":"family"},{"index":10,"strongs":0,"text":"of the"},{"index":11,"strongs":"H06180","text":"Erites:"}]},{"chapter":26,"text":"Of Arod, the family of the Arodites: of Areli, the family of the Arelites.","verse":17,"book":"Numbers","reference":[{"index":0,"strongs":0,"text":"Of "},{"index":1,"strongs":"H0720","text":"Arod,"},{"index":2,"strongs":0,"text":"the"},{"index":3,"strongs":"H04940","text":"family"},{"index":4,"strongs":0,"text":"of the"},{"index":5,"strongs":"H0722","text":"Arodites:"},{"index":6,"strongs":0,"text":"of"},{"index":7,"strongs":"H0692","text":"Areli,"},{"index":8,"strongs":0,"text":"the"},{"index":9,"strongs":"H04940","text":"family"},{"index":10,"strongs":0,"text":"of the"},{"index":11,"strongs":"H0692","text":"Arelites."}]},{"chapter":26,"text":"These [are] the families of the children of Gad according to those that were numbered of them, forty thousand and five hundred.","verse":18,"book":"Numbers","reference":[{"index":0,"strongs":0,"text":"These are the "},{"index":1,"strongs":"H04940","text":"families"},{"index":2,"strongs":0,"text":"of the"},{"index":3,"strongs":"H01121","text":"children"},{"index":4,"strongs":0,"text":"of"},{"index":5,"strongs":"H01410","text":"Gad"},{"index":6,"strongs":0,"text":"according to those that were"},{"index":7,"strongs":"H06485","text":"numbered"},{"index":8,"strongs":0,"text":"of them,"},{"index":9,"strongs":"H0705","text":"forty"},{"index":10,"strongs":"H0505","text":"thousand"},{"index":11,"strongs":0,"text":"and"},{"index":12,"strongs":"H02568","text":"five"},{"index":13,"strongs":"H03967","text":"hundred."}]},{"chapter":26,"text":"The sons of Judah [were] Er and Onan: and Er and Onan died in the land of Canaan.","verse":19,"book":"Numbers","reference":[{"index":0,"strongs":0,"text":"The "},{"index":1,"strongs":"H01121","text":"sons"},{"index":2,"strongs":0,"text":"of"},{"index":3,"strongs":"H03063","text":"Judah"},{"index":4,"strongs":0,"text":"were"},{"index":5,"strongs":"H06147","text":"Er"},{"index":6,"strongs":0,"text":"and"},{"index":7,"strongs":"H0209","text":"Onan:"},{"index":8,"strongs":0,"text":"and"},{"index":9,"strongs":"H06147","text":"Er"},{"index":10,"strongs":0,"text":"and"},{"index":11,"strongs":"H0209","text":"Onan"},{"index":12,"strongs":"H04191","text":"died"},{"index":13,"strongs":0,"text":"in the"},{"index":14,"strongs":"H0776","text":"land"},{"index":15,"strongs":0,"text":"of"},{"index":16,"strongs":"H03667","text":"Canaan."}]},{"chapter":26,"text":"And the sons of Judah after their families were; of Shelah, the family of the Shelanites: of Pharez, the family of the Pharzites: of Zerah, the family of the Zarhites.","verse":20,"book":"Numbers","reference":[{"index":0,"strongs":0,"text":"And the "},{"index":1,"strongs":"H01121","text":"sons"},{"index":2,"strongs":0,"text":"of"},{"index":3,"strongs":"H03063","text":"Judah"},{"index":4,"strongs":0,"text":"after their"},{"index":5,"strongs":"H04940","text":"families"},{"index":6,"strongs":0,"text":"were; of"},{"index":7,"strongs":"H07956","text":"Shelah,"},{"index":8,"strongs":0,"text":"the"},{"index":9,"strongs":"H04940","text":"family"},{"index":10,"strongs":0,"text":"of the"},{"index":11,"strongs":"H08024","text":"Shelanites:"},{"index":12,"strongs":0,"text":"of"},{"index":13,"strongs":"H06557","text":"Pharez,"},{"index":14,"strongs":0,"text":"the"},{"index":15,"strongs":"H04940","text":"family"},{"index":16,"strongs":0,"text":"of the"},{"index":17,"strongs":"H06558","text":"Pharzites:"},{"index":18,"strongs":0,"text":"of"},{"index":19,"strongs":"H02226","text":"Zerah,"},{"index":20,"strongs":0,"text":"the"},{"index":21,"strongs":"H04940","text":"family"},{"index":22,"strongs":0,"text":"of the"},{"index":23,"strongs":"H02227","text":"Zarhites."}]},{"chapter":26,"text":"And the sons of Pharez were; of Hezron, the family of the Hezronites: of Hamul, the family of the Hamulites.","verse":21,"book":"Numbers","reference":[{"index":0,"strongs":0,"text":"And the "},{"index":1,"strongs":"H01121","text":"sons"},{"index":2,"strongs":0,"text":"of"},{"index":3,"strongs":"H06557","text":"Pharez"},{"index":4,"strongs":0,"text":"were; of"},{"index":5,"strongs":"H02696","text":"Hezron,"},{"index":6,"strongs":0,"text":"the"},{"index":7,"strongs":"H04940","text":"family"},{"index":8,"strongs":0,"text":"of the"},{"index":9,"strongs":"H02697","text":"Hezronites:"},{"index":10,"strongs":0,"text":"of"},{"index":11,"strongs":"H02538","text":"Hamul,"},{"index":12,"strongs":0,"text":"the"},{"index":13,"strongs":"H04940","text":"family"},{"index":14,"strongs":0,"text":"of the"},{"index":15,"strongs":"H02539","text":"Hamulites."}]},{"chapter":26,"text":"These [are] the families of Judah according to those that were numbered of them, threescore and sixteen thousand and five hundred.","verse":22,"book":"Numbers","reference":[{"index":0,"strongs":0,"text":"These are the "},{"index":1,"strongs":"H04940","text":"families"},{"index":2,"strongs":0,"text":"of"},{"index":3,"strongs":"H03063","text":"Judah"},{"index":4,"strongs":0,"text":"according to those that were"},{"index":5,"strongs":"H06485","text":"numbered"},{"index":6,"strongs":0,"text":"of them, threescore and"},{"index":7,"strongs":"H08337","text":"sixteen"},{"index":8,"strongs":"H07657","text":"thousand"},{"index":9,"strongs":"H0505","text":"and"},{"index":10,"strongs":0,"text":"five"},{"index":11,"strongs":"H02568","text":"hundred."}]},{"chapter":26,"text":"[Of] the sons of Issachar after their families: [of] Tola, the family of the Tolaites: of Pua, the family of the Punites:","verse":23,"book":"Numbers","reference":[{"index":0,"strongs":0,"text":"Of the "},{"index":1,"strongs":"H01121","text":"sons"},{"index":2,"strongs":0,"text":"of"},{"index":3,"strongs":"H03485","text":"Issachar"},{"index":4,"strongs":0,"text":"after their"},{"index":5,"strongs":"H04940","text":"families:"},{"index":6,"strongs":0,"text":"of"},{"index":7,"strongs":"H08439","text":"Tola,"},{"index":8,"strongs":0,"text":"the"},{"index":9,"strongs":"H04940","text":"family"},{"index":10,"strongs":0,"text":"of the"},{"index":11,"strongs":"H08440","text":"Tolaites:"},{"index":12,"strongs":0,"text":"of"},{"index":13,"strongs":"H06312","text":"Pua,"},{"index":14,"strongs":0,"text":"the"},{"index":15,"strongs":"H04940","text":"family"},{"index":16,"strongs":0,"text":"of the"},{"index":17,"strongs":"H06324","text":"Punites:"}]},{"chapter":26,"text":"Of Jashub, the family of the Jashubites: of Shimron, the family of the Shimronites.","verse":24,"book":"Numbers","reference":[{"index":0,"strongs":0,"text":"Of "},{"index":1,"strongs":"H03437","text":"Jashub,"},{"index":2,"strongs":0,"text":"the"},{"index":3,"strongs":"H04940","text":"family"},{"index":4,"strongs":0,"text":"of the"},{"index":5,"strongs":"H03432","text":"Jashubites:"},{"index":6,"strongs":0,"text":"of"},{"index":7,"strongs":"H08110","text":"Shimron,"},{"index":8,"strongs":0,"text":"the"},{"index":9,"strongs":"H04940","text":"family"},{"index":10,"strongs":0,"text":"of the"},{"index":11,"strongs":"H08117","text":"Shimronites."}]},{"chapter":26,"text":"These [are] the families of Issachar according to those that were numbered of them, threescore and four thousand and three hundred.","verse":25,"book":"Numbers","reference":[{"index":0,"strongs":0,"text":"These are the "},{"index":1,"strongs":"H04940","text":"families"},{"index":2,"strongs":0,"text":"of"},{"index":3,"strongs":"H03485","text":"Issachar"},{"index":4,"strongs":0,"text":"according to those that were"},{"index":5,"strongs":"H06485","text":"numbered"},{"index":6,"strongs":0,"text":"of them,"},{"index":7,"strongs":"H08346","text":"threescore"},{"index":8,"strongs":0,"text":"and"},{"index":9,"strongs":"H0702","text":"four"},{"index":10,"strongs":"H0505","text":"thousand"},{"index":11,"strongs":0,"text":"and"},{"index":12,"strongs":"H07969","text":"three"},{"index":13,"strongs":"H03967","text":"hundred."}]},{"chapter":26,"text":"[Of] the sons of Zebulun after their families: of Sered, the family of the Sardites: of Elon, the family of the Elonites: of Jahleel, the family of the Jahleelites.","verse":26,"book":"Numbers","reference":[{"index":0,"strongs":0,"text":"Of the "},{"index":1,"strongs":"H01121","text":"sons"},{"index":2,"strongs":0,"text":"of"},{"index":3,"strongs":"H02074","text":"Zebulun"},{"index":4,"strongs":0,"text":"after their"},{"index":5,"strongs":"H04940","text":"families:"},{"index":6,"strongs":0,"text":"of"},{"index":7,"strongs":"H05624","text":"Sered,"},{"index":8,"strongs":0,"text":"the"},{"index":9,"strongs":"H04940","text":"family"},{"index":10,"strongs":0,"text":"of the"},{"index":11,"strongs":"H05625","text":"Sardites:"},{"index":12,"strongs":0,"text":"of"},{"index":13,"strongs":"H0356","text":"Elon,"},{"index":14,"strongs":0,"text":"the"},{"index":15,"strongs":"H04940","text":"family"},{"index":16,"strongs":0,"text":"of the"},{"index":17,"strongs":"H0440","text":"Elonites:"},{"index":18,"strongs":0,"text":"of"},{"index":19,"strongs":"H03177","text":"Jahleel,"},{"index":20,"strongs":0,"text":"the"},{"index":21,"strongs":"H04940","text":"family"},{"index":22,"strongs":0,"text":"of the"},{"index":23,"strongs":"H03178","text":"Jahleelites."}]},{"chapter":26,"text":"These [are] the families of the Zebulunites according to those that were numbered of them, threescore thousand and five hundred.","verse":27,"book":"Numbers","reference":[{"index":0,"strongs":0,"text":"These are the "},{"index":1,"strongs":"H04940","text":"families"},{"index":2,"strongs":0,"text":"of the"},{"index":3,"strongs":"H02075","text":"Zebulunites"},{"index":4,"strongs":0,"text":"according to those that were"},{"index":5,"strongs":"H06485","text":"numbered"},{"index":6,"strongs":0,"text":"of them,"},{"index":7,"strongs":"H08346","text":"threescore"},{"index":8,"strongs":"H0505","text":"thousand"},{"index":9,"strongs":0,"text":"and"},{"index":10,"strongs":"H02568","text":"five"},{"index":11,"strongs":"H03967","text":"hundred."}]},{"chapter":26,"text":"The sons of Joseph after their families [were] Manasseh and Ephraim.","verse":28,"book":"Numbers","reference":[{"index":0,"strongs":0,"text":"The "},{"index":1,"strongs":"H01121","text":"sons"},{"index":2,"strongs":0,"text":"of"},{"index":3,"strongs":"H03130","text":"Joseph"},{"index":4,"strongs":0,"text":"after their"},{"index":5,"strongs":"H04940","text":"families"},{"index":6,"strongs":0,"text":"were"},{"index":7,"strongs":"H04519","text":"Manasseh"},{"index":8,"strongs":0,"text":"and"},{"index":9,"strongs":"H0669","text":"Ephraim."}]},{"chapter":26,"text":"Of the sons of Manasseh: of Machir, the family of the Machirites: and Machir begat Gilead: of Gilead [come] the family of the Gileadites.","verse":29,"book":"Numbers","reference":[{"index":0,"strongs":0,"text":"Of the "},{"index":1,"strongs":"H01121","text":"sons"},{"index":2,"strongs":0,"text":"of"},{"index":3,"strongs":"H04519","text":"Manasseh:"},{"index":4,"strongs":0,"text":"of"},{"index":5,"strongs":"H04353","text":"Machir,"},{"index":6,"strongs":0,"text":"the"},{"index":7,"strongs":"H04940","text":"family"},{"index":8,"strongs":0,"text":"of the"},{"index":9,"strongs":"H04354","text":"Machirites:"},{"index":10,"strongs":0,"text":"and"},{"index":11,"strongs":"H04353","text":"Machir"},{"index":12,"strongs":"H03205","text":"begat"},{"index":13,"strongs":"H01568","text":"Gilead:"},{"index":14,"strongs":0,"text":"of"},{"index":15,"strongs":"H01568","text":"Gilead"},{"index":16,"strongs":0,"text":"come the"},{"index":17,"strongs":"H04940","text":"family"},{"index":18,"strongs":0,"text":"of the"},{"index":19,"strongs":"H01569","text":"Gileadites."}]},{"chapter":26,"text":"These [are] the sons of Gilead: [of] Jeezer, the family of the Jeezerites: of Helek, the family of the Helekites:","verse":30,"book":"Numbers","reference":[{"index":0,"strongs":0,"text":"These are the "},{"index":1,"strongs":"H01121","text":"sons"},{"index":2,"strongs":0,"text":"of"},{"index":3,"strongs":"H01568","text":"Gilead:"},{"index":4,"strongs":0,"text":"of"},{"index":5,"strongs":"H0372","text":"Jeezer,"},{"index":6,"strongs":0,"text":"the"},{"index":7,"strongs":"H04940","text":"family"},{"index":8,"strongs":0,"text":"of the"},{"index":9,"strongs":"H0373","text":"Jeezerites:"},{"index":10,"strongs":0,"text":"of"},{"index":11,"strongs":"H02507","text":"Helek,"},{"index":12,"strongs":0,"text":"the"},{"index":13,"strongs":"H04940","text":"family"},{"index":14,"strongs":0,"text":"of the"},{"index":15,"strongs":"H02516","text":"Helekites:"}]},{"chapter":26,"text":"And [of] Asriel, the family of the Asrielites: and [of] Shechem, the family of the Shechemites:","verse":31,"book":"Numbers","reference":[{"index":0,"strongs":0,"text":"And of "},{"index":1,"strongs":"H0844","text":"Asriel,"},{"index":2,"strongs":0,"text":"the"},{"index":3,"strongs":"H04940","text":"family"},{"index":4,"strongs":0,"text":"of the"},{"index":5,"strongs":"H0845","text":"Asrielites:"},{"index":6,"strongs":0,"text":"and of"},{"index":7,"strongs":"H07928","text":"Shechem,"},{"index":8,"strongs":0,"text":"the"},{"index":9,"strongs":"H04940","text":"family"},{"index":10,"strongs":0,"text":"of the"},{"index":11,"strongs":"H07930","text":"Shechemites:"}]},{"chapter":26,"text":"And [of] Shemida, the family of the Shemidaites: and [of] Hepher, the family of the Hepherites.","verse":32,"book":"Numbers","reference":[{"index":0,"strongs":0,"text":"And of "},{"index":1,"strongs":"H08061","text":"Shemida,"},{"index":2,"strongs":0,"text":"the"},{"index":3,"strongs":"H04940","text":"family"},{"index":4,"strongs":0,"text":"of the"},{"index":5,"strongs":"H08062","text":"Shemidaites:"},{"index":6,"strongs":0,"text":"and of"},{"index":7,"strongs":"H02660","text":"Hepher,"},{"index":8,"strongs":0,"text":"the"},{"index":9,"strongs":"H04940","text":"family"},{"index":10,"strongs":0,"text":"of the"},{"index":11,"strongs":"H02662","text":"Hepherites."}]},{"chapter":26,"text":"And Zelophehad the son of Hepher had no sons, but daughters: and the names of the daughters of Zelophehad [were] Mahlah, and Noah, Hoglah, Milcah, and Tirzah.","verse":33,"book":"Numbers","reference":[{"index":0,"strongs":0,"text":"And "},{"index":1,"strongs":"H06765","text":"Zelophehad"},{"index":2,"strongs":0,"text":"the"},{"index":3,"strongs":"H01121","text":"son"},{"index":4,"strongs":0,"text":"of"},{"index":5,"strongs":"H02660","text":"Hepher"},{"index":6,"strongs":0,"text":"had no"},{"index":7,"strongs":"H01121","text":"sons,"},{"index":8,"strongs":0,"text":"but"},{"index":9,"strongs":"H01323","text":"daughters:"},{"index":10,"strongs":0,"text":"and the"},{"index":11,"strongs":"H08034","text":"names"},{"index":12,"strongs":0,"text":"of the"},{"index":13,"strongs":"H01323","text":"daughters"},{"index":14,"strongs":0,"text":"of"},{"index":15,"strongs":"H06765","text":"Zelophehad"},{"index":16,"strongs":0,"text":"were"},{"index":17,"strongs":"H04244","text":"Mahlah,"},{"index":18,"strongs":0,"text":"and"},{"index":19,"strongs":"H05270","text":"Noah,"},{"index":20,"strongs":"H02295","text":"Hoglah,"},{"index":21,"strongs":"H04435","text":"Milcah,"},{"index":22,"strongs":0,"text":"and"},{"index":23,"strongs":"H08656","text":"Tirzah."}]},{"chapter":26,"text":"These [are] the families of Manasseh, and those that were numbered of them, fifty and two thousand and seven hundred.","verse":34,"book":"Numbers","reference":[{"index":0,"strongs":0,"text":"These are the "},{"index":1,"strongs":"H04940","text":"families"},{"index":2,"strongs":0,"text":"of"},{"index":3,"strongs":"H04519","text":"Manasseh,"},{"index":4,"strongs":0,"text":"and those that were"},{"index":5,"strongs":"H06485","text":"numbered"},{"index":6,"strongs":0,"text":"of them,"},{"index":7,"strongs":"H02572","text":"fifty"},{"index":8,"strongs":0,"text":"and"},{"index":9,"strongs":"H08147","text":"two"},{"index":10,"strongs":"H0505","text":"thousand"},{"index":11,"strongs":0,"text":"and"},{"index":12,"strongs":"H07651","text":"seven"},{"index":13,"strongs":"H03967","text":"hundred."}]},{"chapter":26,"text":"These [are] the sons of Ephraim after their families: of Shuthelah, the family of the Shuthalhites: of Becher, the family of the Bachrites: of Tahan, the family of the Tahanites.","verse":35,"book":"Numbers","reference":[{"index":0,"strongs":0,"text":"These are the "},{"index":1,"strongs":"H01121","text":"sons"},{"index":2,"strongs":0,"text":"of"},{"index":3,"strongs":"H0669","text":"Ephraim"},{"index":4,"strongs":0,"text":"after their"},{"index":5,"strongs":"H04940","text":"families:"},{"index":6,"strongs":0,"text":"of"},{"index":7,"strongs":"H07803","text":"Shuthelah,"},{"index":8,"strongs":0,"text":"the"},{"index":9,"strongs":"H04940","text":"family"},{"index":10,"strongs":0,"text":"of the"},{"index":11,"strongs":"H08364","text":"Shuthalhites:"},{"index":12,"strongs":0,"text":"of"},{"index":13,"strongs":"H01071","text":"Becher,"},{"index":14,"strongs":0,"text":"the"},{"index":15,"strongs":"H04940","text":"family"},{"index":16,"strongs":0,"text":"of the"},{"index":17,"strongs":"H01076","text":"Bachrites:"},{"index":18,"strongs":0,"text":"of"},{"index":19,"strongs":"H08465","text":"Tahan,"},{"index":20,"strongs":0,"text":"the"},{"index":21,"strongs":"H04940","text":"family"},{"index":22,"strongs":0,"text":"of the"},{"index":23,"strongs":"H08470","text":"Tahanites."}]},{"chapter":26,"text":"And these [are] the sons of Shuthelah: of Eran, the family of the Eranites.","verse":36,"book":"Numbers","reference":[{"index":0,"strongs":0,"text":"And these are the "},{"index":1,"strongs":"H01121","text":"sons"},{"index":2,"strongs":0,"text":"of"},{"index":3,"strongs":"H07803","text":"Shuthelah:"},{"index":4,"strongs":0,"text":"of"},{"index":5,"strongs":"H06197","text":"Eran,"},{"index":6,"strongs":0,"text":"the"},{"index":7,"strongs":"H04940","text":"family"},{"index":8,"strongs":0,"text":"of the"},{"index":9,"strongs":"H06198","text":"Eranites."}]},{"chapter":26,"text":"These [are] the families of the sons of Ephraim according to those that were numbered of them, thirty and two thousand and five hundred. These [are] the sons of Joseph after their families.","verse":37,"book":"Numbers","reference":[{"index":0,"strongs":0,"text":"These are the "},{"index":1,"strongs":"H04940","text":"families"},{"index":2,"strongs":0,"text":"of the"},{"index":3,"strongs":"H01121","text":"sons"},{"index":4,"strongs":0,"text":"of"},{"index":5,"strongs":"H0669","text":"Ephraim"},{"index":6,"strongs":0,"text":"according to those that were"},{"index":7,"strongs":"H06485","text":"numbered"},{"index":8,"strongs":0,"text":"of them,"},{"index":9,"strongs":"H07970","text":"thirty"},{"index":10,"strongs":0,"text":"and"},{"index":11,"strongs":"H08147","text":"two"},{"index":12,"strongs":"H0505","text":"thousand"},{"index":13,"strongs":0,"text":"and"},{"index":14,"strongs":"H02568","text":"five"},{"index":15,"strongs":"H03967","text":"hundred."},{"index":16,"strongs":0,"text":"These are the"},{"index":17,"strongs":"H01121","text":"sons"},{"index":18,"strongs":0,"text":"of"},{"index":19,"strongs":"H03130","text":"Joseph"},{"index":20,"strongs":0,"text":"after their"},{"index":21,"strongs":"H04940","text":"families."}]},{"chapter":26,"text":"The sons of Benjamin after their families: of Bela, the family of the Belaites: of Ashbel, the family of the Ashbelites: of Ahiram, the family of the Ahiramites:","verse":38,"book":"Numbers","reference":[{"index":0,"strongs":0,"text":"The "},{"index":1,"strongs":"H01121","text":"sons"},{"index":2,"strongs":0,"text":"of"},{"index":3,"strongs":"H01144","text":"Benjamin"},{"index":4,"strongs":0,"text":"after their"},{"index":5,"strongs":"H04940","text":"families:"},{"index":6,"strongs":0,"text":"of"},{"index":7,"strongs":"H01106","text":"Bela,"},{"index":8,"strongs":0,"text":"the"},{"index":9,"strongs":"H04940","text":"family"},{"index":10,"strongs":0,"text":"of the"},{"index":11,"strongs":"H01108","text":"Belaites:"},{"index":12,"strongs":0,"text":"of"},{"index":13,"strongs":"H0788","text":"Ashbel,"},{"index":14,"strongs":0,"text":"the"},{"index":15,"strongs":"H04940","text":"family"},{"index":16,"strongs":0,"text":"of the"},{"index":17,"strongs":"H0789","text":"Ashbelites:"},{"index":18,"strongs":0,"text":"of"},{"index":19,"strongs":"H0297","text":"Ahiram,"},{"index":20,"strongs":0,"text":"the"},{"index":21,"strongs":"H04940","text":"family"},{"index":22,"strongs":0,"text":"of the"},{"index":23,"strongs":"H0298","text":"Ahiramites:"}]},{"chapter":26,"text":"Of Shupham, the family of the Shuphamites: of Hupham, the family of the Huphamites.","verse":39,"book":"Numbers","reference":[{"index":0,"strongs":0,"text":"Of "},{"index":1,"strongs":"H08197","text":"Shupham,"},{"index":2,"strongs":0,"text":"the"},{"index":3,"strongs":"H04940","text":"family"},{"index":4,"strongs":0,"text":"of the"},{"index":5,"strongs":"H07781","text":"Shuphamites:"},{"index":6,"strongs":0,"text":"of"},{"index":7,"strongs":"H02349","text":"Hupham,"},{"index":8,"strongs":0,"text":"the"},{"index":9,"strongs":"H04940","text":"family"},{"index":10,"strongs":0,"text":"of the"},{"index":11,"strongs":"H02350","text":"Huphamites."}]},{"chapter":26,"text":"And the sons of Bela were Ard and Naaman: [of Ard,] the family of the Ardites: [and] of Naaman, the family of the Naamites.","verse":40,"book":"Numbers","reference":[{"index":0,"strongs":0,"text":"And the "},{"index":1,"strongs":"H01121","text":"sons"},{"index":2,"strongs":0,"text":"of"},{"index":3,"strongs":"H01106","text":"Bela"},{"index":4,"strongs":0,"text":"were"},{"index":5,"strongs":"H0714","text":"ard"},{"index":6,"strongs":0,"text":"and"},{"index":7,"strongs":"H05283","text":"Naaman:"},{"index":8,"strongs":0,"text":"of Ard, the"},{"index":9,"strongs":"H04940","text":"family"},{"index":10,"strongs":0,"text":"of the"},{"index":11,"strongs":"H0716","text":"Ardites:"},{"index":12,"strongs":0,"text":"and of"},{"index":13,"strongs":"H05283","text":"Naaman,"},{"index":14,"strongs":0,"text":"the"},{"index":15,"strongs":"H04940","text":"family"},{"index":16,"strongs":0,"text":"of the"},{"index":17,"strongs":"H05280","text":"Naamites."}]},{"chapter":26,"text":"These [are] the sons of Benjamin after their families: and they that were numbered of them [were] forty and five thousand and six hundred.","verse":41,"book":"Numbers","reference":[{"index":0,"strongs":0,"text":"These are the "},{"index":1,"strongs":"H01121","text":"sons"},{"index":2,"strongs":0,"text":"of"},{"index":3,"strongs":"H01144","text":"Benjamin"},{"index":4,"strongs":0,"text":"after their"},{"index":5,"strongs":"H04940","text":"families:"},{"index":6,"strongs":0,"text":"and they that were"},{"index":7,"strongs":"H06485","text":"numbered"},{"index":8,"strongs":0,"text":"of them were"},{"index":9,"strongs":"H0705","text":"forty"},{"index":10,"strongs":0,"text":"and"},{"index":11,"strongs":"H02568","text":"five"},{"index":12,"strongs":"H0505","text":"thousand"},{"index":13,"strongs":0,"text":"and"},{"index":14,"strongs":"H08337","text":"six"},{"index":15,"strongs":"H03967","text":"hundred."}]},{"chapter":26,"text":"These [are] the sons of Dan after their families: of Shuham, the family of the Shuhamites. These [are] the families of Dan after their families.","verse":42,"book":"Numbers","reference":[{"index":0,"strongs":0,"text":"These are the "},{"index":1,"strongs":"H01121","text":"sons"},{"index":2,"strongs":0,"text":"of"},{"index":3,"strongs":"H01835","text":"Dan"},{"index":4,"strongs":0,"text":"after their"},{"index":5,"strongs":"H04940","text":"families:"},{"index":6,"strongs":0,"text":"of"},{"index":7,"strongs":"H07748","text":"Shuham,"},{"index":8,"strongs":0,"text":"the"},{"index":9,"strongs":"H04940","text":"family"},{"index":10,"strongs":0,"text":"of the"},{"index":11,"strongs":"H07749","text":"Shuhamites."},{"index":12,"strongs":0,"text":"These are the"},{"index":13,"strongs":"H04940","text":"families"},{"index":14,"strongs":0,"text":"of"},{"index":15,"strongs":"H01835","text":"Dan"},{"index":16,"strongs":0,"text":"after their"},{"index":17,"strongs":"H04940","text":"families."}]},{"chapter":26,"text":"All the families of the Shuhamites, according to those that were numbered of them, [were] threescore and four thousand and four hundred.","verse":43,"book":"Numbers","reference":[{"index":0,"strongs":0,"text":"All the "},{"index":1,"strongs":"H04940","text":"families"},{"index":2,"strongs":0,"text":"of the"},{"index":3,"strongs":"H07749","text":"Shuhamites,"},{"index":4,"strongs":0,"text":"according to those that were"},{"index":5,"strongs":"H06485","text":"numbered"},{"index":6,"strongs":0,"text":"of them, were"},{"index":7,"strongs":"H08346","text":"threescore"},{"index":8,"strongs":0,"text":"and"},{"index":9,"strongs":"H0702","text":"four"},{"index":10,"strongs":"H0505","text":"thousand"},{"index":11,"strongs":0,"text":"and"},{"index":12,"strongs":"H0702","text":"four"},{"index":13,"strongs":"H03967","text":"hundred."}]},{"chapter":26,"text":"[Of] the children of Asher after their families: of Jimna, the family of the Jimnites: of Jesui, the family of the Jesuites: of Beriah, the family of the Beriites.","verse":44,"book":"Numbers","reference":[{"index":0,"strongs":0,"text":"Of the "},{"index":1,"strongs":"H01121","text":"children"},{"index":2,"strongs":0,"text":"of"},{"index":3,"strongs":"H0836","text":"Asher"},{"index":4,"strongs":0,"text":"after their"},{"index":5,"strongs":"H04940","text":"families:"},{"index":6,"strongs":0,"text":"of"},{"index":7,"strongs":"H03232","text":"Jimna,"},{"index":8,"strongs":0,"text":"the"},{"index":9,"strongs":"H04940","text":"family"},{"index":10,"strongs":0,"text":"of the"},{"index":11,"strongs":"H03232","text":"Jimnites:"},{"index":12,"strongs":0,"text":"of"},{"index":13,"strongs":"H03440","text":"Jesui,"},{"index":14,"strongs":0,"text":"the"},{"index":15,"strongs":"H04940","text":"family"},{"index":16,"strongs":0,"text":"of the"},{"index":17,"strongs":"H03441","text":"Jesuites:"},{"index":18,"strongs":0,"text":"of"},{"index":19,"strongs":"H01283","text":"Beriah,"},{"index":20,"strongs":0,"text":"the"},{"index":21,"strongs":"H04940","text":"family"},{"index":22,"strongs":0,"text":"of the"},{"index":23,"strongs":"H01284","text":"Beriites."}]},{"chapter":26,"text":"Of the sons of Beriah: of Heber, the family of the Heberites: of Malchiel, the family of the Malchielites.","verse":45,"book":"Numbers","reference":[{"index":0,"strongs":0,"text":"Of the "},{"index":1,"strongs":"H01121","text":"sons"},{"index":2,"strongs":0,"text":"of"},{"index":3,"strongs":"H01283","text":"Beriah:"},{"index":4,"strongs":0,"text":"of"},{"index":5,"strongs":"H02268","text":"Heber,"},{"index":6,"strongs":0,"text":"the"},{"index":7,"strongs":"H04940","text":"family"},{"index":8,"strongs":0,"text":"of the"},{"index":9,"strongs":"H02277","text":"Heberites:"},{"index":10,"strongs":0,"text":"of"},{"index":11,"strongs":"H04439","text":"Malchiel,"},{"index":12,"strongs":0,"text":"the"},{"index":13,"strongs":"H04940","text":"family"},{"index":14,"strongs":0,"text":"of the"},{"index":15,"strongs":"H04440","text":"Malchielites."}]},{"chapter":26,"text":"And the name of the daughter of Asher [was] Sarah.","verse":46,"book":"Numbers","reference":[{"index":0,"strongs":0,"text":"And the "},{"index":1,"strongs":"H08034","text":"name"},{"index":2,"strongs":0,"text":"of the"},{"index":3,"strongs":"H01323","text":"daughter"},{"index":4,"strongs":0,"text":"of"},{"index":5,"strongs":"H0836","text":"Asher"},{"index":6,"strongs":0,"text":"was"},{"index":7,"strongs":"H08294","text":"Sarah."}]},{"chapter":26,"text":"These [are] the families of the sons of Asher according to those that were numbered of them; [who were] fifty and three thousand and four hundred.","verse":47,"book":"Numbers","reference":[{"index":0,"strongs":0,"text":"These are the "},{"index":1,"strongs":"H04940","text":"families"},{"index":2,"strongs":0,"text":"of the"},{"index":3,"strongs":"H01121","text":"sons"},{"index":4,"strongs":0,"text":"of"},{"index":5,"strongs":"H0836","text":"Asher"},{"index":6,"strongs":0,"text":"according to those that were"},{"index":7,"strongs":"H06485","text":"numbered"},{"index":8,"strongs":0,"text":"of them; who were"},{"index":9,"strongs":"H02572","text":"fifty"},{"index":10,"strongs":0,"text":"and"},{"index":11,"strongs":"H07969","text":"three"},{"index":12,"strongs":"H0505","text":"thousand"},{"index":13,"strongs":0,"text":"and"},{"index":14,"strongs":"H0702","text":"four"},{"index":15,"strongs":"H03967","text":"hundred."}]},{"chapter":26,"text":"[Of] the sons of Naphtali after their families: of Jahzeel, the family of the Jahzeelites: of Guni, the family of the Gunites:","verse":48,"book":"Numbers","reference":[{"index":0,"strongs":0,"text":"Of the "},{"index":1,"strongs":"H01121","text":"sons"},{"index":2,"strongs":0,"text":"of"},{"index":3,"strongs":"H05321","text":"Naphtali"},{"index":4,"strongs":0,"text":"after their"},{"index":5,"strongs":"H04940","text":"families:"},{"index":6,"strongs":0,"text":"of"},{"index":7,"strongs":"H03183","text":"Jahzeel,"},{"index":8,"strongs":0,"text":"the"},{"index":9,"strongs":"H04940","text":"family"},{"index":10,"strongs":0,"text":"of the"},{"index":11,"strongs":"H03184","text":"Jahzeelites:"},{"index":12,"strongs":0,"text":"of"},{"index":13,"strongs":"H01476","text":"Guni,"},{"index":14,"strongs":0,"text":"the"},{"index":15,"strongs":"H04940","text":"family"},{"index":16,"strongs":0,"text":"of the"},{"index":17,"strongs":"H01477","text":"Gunites:"}]},{"chapter":26,"text":"Of Jezer, the family of the Jezerites: of Shillem, the family of the Shillemites.","verse":49,"book":"Numbers","reference":[{"index":0,"strongs":0,"text":"Of "},{"index":1,"strongs":"H03337","text":"Jezer,"},{"index":2,"strongs":0,"text":"the"},{"index":3,"strongs":"H04940","text":"family"},{"index":4,"strongs":0,"text":"of the"},{"index":5,"strongs":"H03340","text":"Jezerites:"},{"index":6,"strongs":0,"text":"of"},{"index":7,"strongs":"H08006","text":"Shillem,"},{"index":8,"strongs":0,"text":"the"},{"index":9,"strongs":"H04940","text":"family"},{"index":10,"strongs":0,"text":"of the"},{"index":11,"strongs":"H08016","text":"Shillemites."}]},{"chapter":26,"text":"These [are] the families of Naphtali according to their families: and they that were numbered of them [were] forty and five thousand and four hundred.","verse":50,"book":"Numbers","reference":[{"index":0,"strongs":0,"text":"These are the "},{"index":1,"strongs":"H04940","text":"families"},{"index":2,"strongs":0,"text":"of"},{"index":3,"strongs":"H05321","text":"Naphtali"},{"index":4,"strongs":0,"text":"according to their"},{"index":5,"strongs":"H04940","text":"families:"},{"index":6,"strongs":0,"text":"and they that were"},{"index":7,"strongs":"H06485","text":"numbered"},{"index":8,"strongs":0,"text":"of them were"},{"index":9,"strongs":"H0705","text":"forty"},{"index":10,"strongs":0,"text":"and"},{"index":11,"strongs":"H02568","text":"five"},{"index":12,"strongs":"H0505","text":"thousand"},{"index":13,"strongs":0,"text":"and"},{"index":14,"strongs":"H0702","text":"four"},{"index":15,"strongs":"H03967","text":"hundred."}]},{"chapter":26,"text":"These [were] the numbered of the children of Israel, six hundred thousand and a thousand seven hundred and thirty.","verse":51,"book":"Numbers","reference":[{"index":0,"strongs":0,"text":"These were the "},{"index":1,"strongs":"H06485","text":"numbered"},{"index":2,"strongs":0,"text":"of the"},{"index":3,"strongs":"H01121","text":"children"},{"index":4,"strongs":0,"text":"of"},{"index":5,"strongs":"H03478","text":"Israel,"},{"index":6,"strongs":"H08337","text":"six"},{"index":7,"strongs":"H03967","text":"hundred"},{"index":8,"strongs":"H0505","text":"thousand"},{"index":9,"strongs":0,"text":"and a"},{"index":10,"strongs":"H0505","text":"thousand"},{"index":11,"strongs":"H07651","text":"seven"},{"index":12,"strongs":"H03967","text":"hundred"},{"index":13,"strongs":0,"text":"and"},{"index":14,"strongs":"H07970","text":"thirty."}]},{"chapter":26,"text":"And the LORD spake unto Moses, saying,","verse":52,"book":"Numbers","reference":[{"index":0,"strongs":0,"text":"And the "},{"index":1,"strongs":"H03068","text":"LORD"},{"index":2,"strongs":"H01696","text":"spake"},{"index":3,"strongs":0,"text":"unto"},{"index":4,"strongs":"H04872","text":"Moses,"},{"index":5,"strongs":"H0559","text":"saying,"}]},{"chapter":26,"text":"Unto these the land shall be divided for an inheritance according to the number of names.","verse":53,"book":"Numbers","reference":[{"index":0,"strongs":0,"text":"Unto these the "},{"index":1,"strongs":"H0776","text":"land"},{"index":2,"strongs":0,"text":"shall be"},{"index":3,"strongs":"H02505","text":"divided"},{"index":4,"strongs":0,"text":"for an"},{"index":5,"strongs":"H05159","text":"inheritance"},{"index":6,"strongs":0,"text":"according to the"},{"index":7,"strongs":"H04557","text":"number"},{"index":8,"strongs":0,"text":"of"},{"index":9,"strongs":"H08034","text":"names."}]},{"chapter":26,"text":"To many thou shalt give the more inheritance, and to few thou shalt give the less inheritance: to every one shall his inheritance be given according to those that were numbered of him.","verse":54,"book":"Numbers","reference":[{"index":0,"strongs":0,"text":"To "},{"index":1,"strongs":"H07227","text":"many"},{"index":2,"strongs":0,"text":"thou shalt give the"},{"index":3,"strongs":"H07235","text":"more"},{"index":4,"strongs":"H05159","text":"inheritance,"},{"index":5,"strongs":0,"text":"and to"},{"index":6,"strongs":"H04592","text":"few"},{"index":7,"strongs":0,"text":"thou shalt give the"},{"index":8,"strongs":"H04591","text":"less"},{"index":9,"strongs":"H05159","text":"inheritance:"},{"index":10,"strongs":0,"text":"to every"},{"index":11,"strongs":"H0376","text":"one"},{"index":12,"strongs":0,"text":"shall his"},{"index":13,"strongs":"H05159","text":"inheritance"},{"index":14,"strongs":0,"text":"be"},{"index":15,"strongs":"H05414","text":"given"},{"index":16,"strongs":"H06310","text":"according"},{"index":17,"strongs":0,"text":"to those that were"},{"index":18,"strongs":"H06485","text":"numbered"},{"index":19,"strongs":0,"text":"of him."}]},{"chapter":26,"text":"Notwithstanding the land shall be divided by lot: according to the names of the tribes of their fathers they shall inherit.","verse":55,"book":"Numbers","reference":[{"index":0,"strongs":0,"text":"Notwithstanding the "},{"index":1,"strongs":"H0776","text":"land"},{"index":2,"strongs":0,"text":"shall be"},{"index":3,"strongs":"H02505","text":"divided"},{"index":4,"strongs":0,"text":"by"},{"index":5,"strongs":"H01486","text":"lot:"},{"index":6,"strongs":0,"text":"according to the"},{"index":7,"strongs":"H08034","text":"names"},{"index":8,"strongs":0,"text":"of the"},{"index":9,"strongs":"H04294","text":"tribes"},{"index":10,"strongs":0,"text":"of their"},{"index":11,"strongs":"H0001","text":"fathers"},{"index":12,"strongs":0,"text":"they shall"},{"index":13,"strongs":"H05157","text":"inherit."}]},{"chapter":26,"text":"According to the lot shall the possession thereof be divided between many and few.","verse":56,"book":"Numbers","reference":[{"index":0,"strongs":"H06310","text":"According"},{"index":1,"strongs":0,"text":"to the"},{"index":2,"strongs":"H01486","text":"lot"},{"index":3,"strongs":0,"text":"shall the"},{"index":4,"strongs":"H05159","text":"possession"},{"index":5,"strongs":0,"text":"thereof be"},{"index":6,"strongs":"H02505","text":"divided"},{"index":7,"strongs":0,"text":"between"},{"index":8,"strongs":"H07227","text":"many"},{"index":9,"strongs":0,"text":"and"},{"index":10,"strongs":"H04592","text":"few."}]},{"chapter":26,"text":"And these [are] they that were numbered of the Levites after their families: of Gershon, the family of the Gershonites: of Kohath, the family of the Kohathites: of Merari, the family of the Merarites.","verse":57,"book":"Numbers","reference":[{"index":0,"strongs":0,"text":"And these are they that were "},{"index":1,"strongs":"H06485","text":"numbered"},{"index":2,"strongs":0,"text":"of the"},{"index":3,"strongs":"H03881","text":"Levites"},{"index":4,"strongs":0,"text":"after their"},{"index":5,"strongs":"H04940","text":"families:"},{"index":6,"strongs":0,"text":"of"},{"index":7,"strongs":"H01648","text":"Gershon,"},{"index":8,"strongs":0,"text":"the"},{"index":9,"strongs":"H04940","text":"family"},{"index":10,"strongs":0,"text":"of the"},{"index":11,"strongs":"H01649","text":"Gershonites:"},{"index":12,"strongs":0,"text":"of"},{"index":13,"strongs":"H06955","text":"Kohath,"},{"index":14,"strongs":0,"text":"the"},{"index":15,"strongs":"H04940","text":"family"},{"index":16,"strongs":0,"text":"of the"},{"index":17,"strongs":"H06956","text":"Kohathites:"},{"index":18,"strongs":0,"text":"of"},{"index":19,"strongs":"H04847","text":"Merari,"},{"index":20,"strongs":0,"text":"the"},{"index":21,"strongs":"H04940","text":"family"},{"index":22,"strongs":0,"text":"of the"},{"index":23,"strongs":"H04848","text":"Merarites."}]},{"chapter":26,"text":"These [are] the families of the Levites: the family of the Libnites, the family of the Hebronites, the family of the Mahlites, the family of the Mushites, the family of the Korathites. And Kohath begat Amram.","verse":58,"book":"Numbers","reference":[{"index":0,"strongs":0,"text":"These are the "},{"index":1,"strongs":"H04940","text":"families"},{"index":2,"strongs":0,"text":"of the"},{"index":3,"strongs":"H03881","text":"Levites:"},{"index":4,"strongs":0,"text":"the"},{"index":5,"strongs":"H04940","text":"family"},{"index":6,"strongs":0,"text":"of the"},{"index":7,"strongs":"H03846","text":"Libnites,"},{"index":8,"strongs":0,"text":"the"},{"index":9,"strongs":"H04940","text":"family"},{"index":10,"strongs":0,"text":"of the"},{"index":11,"strongs":"H02276","text":"Hebronites,"},{"index":12,"strongs":0,"text":"the"},{"index":13,"strongs":"H04940","text":"family"},{"index":14,"strongs":0,"text":"of the"},{"index":15,"strongs":"H04250","text":"Mahlites,"},{"index":16,"strongs":0,"text":"the"},{"index":17,"strongs":"H04940","text":"family"},{"index":18,"strongs":0,"text":"of the"},{"index":19,"strongs":"H04188","text":"Mushites,"},{"index":20,"strongs":0,"text":"the"},{"index":21,"strongs":"H04940","text":"family"},{"index":22,"strongs":0,"text":"of the"},{"index":23,"strongs":"H07145","text":"Korathites."},{"index":24,"strongs":0,"text":"And"},{"index":25,"strongs":"H06955","text":"Kohath"},{"index":26,"strongs":"H03205","text":"begat"},{"index":27,"strongs":"H06019","text":"Amram."}]},{"chapter":26,"text":"And the name of Amram's wife [was] Jochebed, the daughter of Levi, whom [her mother] bare to Levi in Egypt: and she bare unto Amram Aaron and Moses, and Miriam their sister.","verse":59,"book":"Numbers","reference":[{"index":0,"strongs":0,"text":"And the "},{"index":1,"strongs":"H08034","text":"name"},{"index":2,"strongs":0,"text":"of"},{"index":3,"strongs":"H06019","text":"Amram's"},{"index":4,"strongs":"H0802","text":"wife"},{"index":5,"strongs":0,"text":"was"},{"index":6,"strongs":"H03115","text":"Jochebed,"},{"index":7,"strongs":0,"text":"the"},{"index":8,"strongs":"H01323","text":"daughter"},{"index":9,"strongs":0,"text":"of"},{"index":10,"strongs":"H03878","text":"Levi,"},{"index":11,"strongs":0,"text":"whom her mother"},{"index":12,"strongs":"H03205","text":"bare"},{"index":13,"strongs":0,"text":"to"},{"index":14,"strongs":"H03878","text":"Levi"},{"index":15,"strongs":0,"text":"in"},{"index":16,"strongs":"H04714","text":"Egypt:"},{"index":17,"strongs":0,"text":"and she"},{"index":18,"strongs":"H03205","text":"bare"},{"index":19,"strongs":0,"text":"unto"},{"index":20,"strongs":"H06019","text":"Amram"},{"index":21,"strongs":"H0175","text":"Aaron"},{"index":22,"strongs":0,"text":"and"},{"index":23,"strongs":"H04872","text":"Moses,"},{"index":24,"strongs":0,"text":"and"},{"index":25,"strongs":"H04813","text":"Miriam"},{"index":26,"strongs":0,"text":"their"},{"index":27,"strongs":"H0269","text":"sister."}]},{"chapter":26,"text":"And unto Aaron was born Nadab, and Abihu, Eleazar, and Ithamar.","verse":60,"book":"Numbers","reference":[{"index":0,"strongs":0,"text":"And unto "},{"index":1,"strongs":"H0175","text":"Aaron"},{"index":2,"strongs":0,"text":"was"},{"index":3,"strongs":"H03205","text":"born"},{"index":4,"strongs":"H05070","text":"Nadab,"},{"index":5,"strongs":0,"text":"and"},{"index":6,"strongs":"H0030","text":"Abihu,"},{"index":7,"strongs":"H0499","text":"Eleazar,"},{"index":8,"strongs":0,"text":"and"},{"index":9,"strongs":"H0385","text":"Ithamar."}]},{"chapter":26,"text":"And Nadab and Abihu died, when they offered strange fire before the LORD.","verse":61,"book":"Numbers","reference":[{"index":0,"strongs":0,"text":"And "},{"index":1,"strongs":"H05070","text":"Nadab"},{"index":2,"strongs":0,"text":"and"},{"index":3,"strongs":"H0030","text":"Abihu"},{"index":4,"strongs":"H04191","text":"died,"},{"index":5,"strongs":0,"text":"when they"},{"index":6,"strongs":"H07126","text":"offered"},{"index":7,"strongs":"H02114","text":"strange"},{"index":8,"strongs":"H0784","text":"fire"},{"index":9,"strongs":"H06440","text":"before"},{"index":10,"strongs":0,"text":"the"},{"index":11,"strongs":"H03068","text":"LORD."}]},{"chapter":26,"text":"And those that were numbered of them were twenty and three thousand, all males from a month old and upward: for they were not numbered among the children of Israel, because there was no inheritance given them among the children of Israel.","verse":62,"book":"Numbers","reference":[{"index":0,"strongs":0,"text":"And those that were "},{"index":1,"strongs":"H06485","text":"numbered"},{"index":2,"strongs":0,"text":"of them were"},{"index":3,"strongs":"H06242","text":"twenty"},{"index":4,"strongs":0,"text":"and"},{"index":5,"strongs":"H07969","text":"three"},{"index":6,"strongs":"H0505","text":"thousand,"},{"index":7,"strongs":0,"text":"all"},{"index":8,"strongs":"H02145","text":"males"},{"index":9,"strongs":0,"text":"from a"},{"index":10,"strongs":"H02320","text":"month"},{"index":11,"strongs":"H01121","text":"old"},{"index":12,"strongs":0,"text":"and"},{"index":13,"strongs":"H04605","text":"upward:"},{"index":14,"strongs":0,"text":"for they were not"},{"index":15,"strongs":"H06485","text":"numbered"},{"index":16,"strongs":"H08432","text":"among"},{"index":17,"strongs":0,"text":"the"},{"index":18,"strongs":"H01121","text":"children"},{"index":19,"strongs":0,"text":"of"},{"index":20,"strongs":"H03478","text":"Israel,"},{"index":21,"strongs":0,"text":"because there was no"},{"index":22,"strongs":"H05159","text":"inheritance"},{"index":23,"strongs":"H05414","text":"given"},{"index":24,"strongs":0,"text":"them"},{"index":25,"strongs":"H08432","text":"among"},{"index":26,"strongs":0,"text":"the"},{"index":27,"strongs":"H01121","text":"children"},{"index":28,"strongs":0,"text":"of"},{"index":29,"strongs":"H03478","text":"Israel."}]},{"chapter":26,"text":"These [are] they that were numbered by Moses and Eleazar the priest, who numbered the children of Israel in the plains of Moab by Jordan [near] Jericho.","verse":63,"book":"Numbers","reference":[{"index":0,"strongs":0,"text":"These are they that were "},{"index":1,"strongs":"H06485","text":"numbered"},{"index":2,"strongs":0,"text":"by"},{"index":3,"strongs":"H04872","text":"Moses"},{"index":4,"strongs":0,"text":"and"},{"index":5,"strongs":"H0499","text":"Eleazar"},{"index":6,"strongs":0,"text":"the"},{"index":7,"strongs":"H03548","text":"priest,"},{"index":8,"strongs":0,"text":"who"},{"index":9,"strongs":"H06485","text":"numbered"},{"index":10,"strongs":0,"text":"the"},{"index":11,"strongs":"H01121","text":"children"},{"index":12,"strongs":0,"text":"of"},{"index":13,"strongs":"H03478","text":"Israel"},{"index":14,"strongs":0,"text":"in the"},{"index":15,"strongs":"H06160","text":"plains"},{"index":16,"strongs":0,"text":"of"},{"index":17,"strongs":"H04124","text":"Moab"},{"index":18,"strongs":0,"text":"by"},{"index":19,"strongs":"H03383","text":"Jordan"},{"index":20,"strongs":0,"text":"near"},{"index":21,"strongs":"H03405","text":"Jericho."}]},{"chapter":26,"text":"But among these there was not a man of them whom Moses and Aaron the priest numbered, when they numbered the children of Israel in the wilderness of Sinai.","verse":64,"book":"Numbers","reference":[{"index":0,"strongs":0,"text":"But among these there was not a "},{"index":1,"strongs":"H0376","text":"man"},{"index":2,"strongs":0,"text":"of them whom"},{"index":3,"strongs":"H04872","text":"Moses"},{"index":4,"strongs":0,"text":"and"},{"index":5,"strongs":"H0175","text":"Aaron"},{"index":6,"strongs":0,"text":"the"},{"index":7,"strongs":"H03548","text":"priest"},{"index":8,"strongs":"H06485","text":"numbered,"},{"index":9,"strongs":0,"text":"when they"},{"index":10,"strongs":"H06485","text":"numbered"},{"index":11,"strongs":0,"text":"the"},{"index":12,"strongs":"H01121","text":"children"},{"index":13,"strongs":0,"text":"of"},{"index":14,"strongs":"H03478","text":"Israel"},{"index":15,"strongs":0,"text":"in the"},{"index":16,"strongs":"H04057","text":"wilderness"},{"index":17,"strongs":0,"text":"of"},{"index":18,"strongs":"H05514","text":"Sinai."}]},{"chapter":26,"text":"For the LORD had said of them, They shall surely die in the wilderness. And there was not left a man of them, save Caleb the son of Jephunneh, and Joshua the son of Nun.","verse":65,"book":"Numbers","reference":[{"index":0,"strongs":0,"text":"For the "},{"index":1,"strongs":"H03068","text":"LORD"},{"index":2,"strongs":0,"text":"had"},{"index":3,"strongs":"H0559","text":"said"},{"index":4,"strongs":0,"text":"of them, They shall"},{"index":5,"strongs":"H04191","text":"surely"},{"index":6,"strongs":"H04191","text":"die"},{"index":7,"strongs":0,"text":"in the"},{"index":8,"strongs":"H04057","text":"wilderness."},{"index":9,"strongs":0,"text":"And there was not"},{"index":10,"strongs":"H03498","text":"left"},{"index":11,"strongs":0,"text":"a"},{"index":12,"strongs":"H0376","text":"man"},{"index":13,"strongs":0,"text":"of them, save"},{"index":14,"strongs":"H03612","text":"Caleb"},{"index":15,"strongs":0,"text":"the"},{"index":16,"strongs":"H01121","text":"son"},{"index":17,"strongs":0,"text":"of"},{"index":18,"strongs":"H03312","text":"Jephunneh,"},{"index":19,"strongs":0,"text":"and"},{"index":20,"strongs":"H03091","text":"Joshua"},{"index":21,"strongs":0,"text":"the"},{"index":22,"strongs":"H01121","text":"son"},{"index":23,"strongs":0,"text":"of"},{"index":24,"strongs":"H05126","text":"Nun."}]}]